{
  "app title": "HRMS System",
  "login": "Login",
  "logout": "Logout",
  "username": "Username",
  "password": "Password",
  "login error": "Invalid username or password",
  "welcome message": "Welcome to HRMS System",
  
  "dashboard": "Dashboard",
  "attendance": "Attendance",
  "leave requests": "Leave Requests",
  "employee directory": "Employee Directory",
  "profile": "My Profile",
  "settings": "Settings",

  "mark attendance": "Mark Attendance",
  "attendance success": "Attendance marked successfully",
  "attendance failed": "Failed to mark attendance",

  "apply leave": "Apply for Leave",
  "leave type": "Leave Type",
  "start date": "Start Date",
  "end date": "End Date",
  "reason": "Reason",
  "submit leave request": "Submit Leave Request",
  "leave request success": "Leave request submitted successfully",

  "employee list": "Employee List",
  "employee name": "Name",
  "employee email": "Email",
  "employee position": "Position",
  "employee department": "Department",

  "profile info": "Profile Information",
  "edit profile": "Edit Profile",
  "save changes": "Save Changes",
  "profile updated": "Profile updated successfully",

  "settings language": "App Language",
  "select language": "Select Language",
  
  "error network": "Network error. Please try again later.",
  "error unknown": "Something went wrong.",

  "button ok": "OK",
  "button cancel": "Cancel",

  "app": "App",
  "title": "Title",
  "login": "Login",
  "logout": "Logout",
  "user": "User",
  "name": "Name",
  "username": "Username",
  "password": "Password",
  "error": "Error",
  "welcome": "Welcome",
  "message": "Message",
  "dashboard": "Dashboard",
  "attendance": "Attendance",
  "leave": "Leave",
  "requests": "Requests",
  "employee": "Employee",
  "directory": "Directory",
  "profile": "Profile",
  "settings": "Settings",
  "mark": "Mark",
  "success": "Success",
  "failed": "Failed",
  "apply": "Apply",
  "type": "Type",
  "start": "Start",
  "date": "Date",
  "end": "End",
  "reason": "Reason",
  "submit": "Submit",
  "list": "List",
  "email": "Email",
  "position": "Position",
  "department": "Department",
  "info": "Information",
  "edit": "Edit",
  "save": "Save",
  "changes": "Changes",
  "updated": "Updated",
  "language": "Language",
  "select": "Select",
  "network": "Network",
  "unknown": "Unknown",
  "button": "Button",
  "ok": "OK",
  "cancel": "Cancel",
  "ccToRequired": "Select CC To is required",
  "attachmentRequired": "Please select attachment.",
  "rejectReasonRequired": "Please select reject reason.",
  "commentRequiredForRejectReasonOther": "Comment is required for reject reason OTHER.",
  "commentRequiredForOther": "Comment is required for reason OTHER.",
  "reasonRequired": "Reason is required.",
  "reasonFieldRequired": "Reason is required.",
  "comment_required_other": "Comment is required for other reason",
"from_time_required": "From Time is required",
"in_date_required": "In Date is required",
"out_date_required": "Out Date is required",
"to_time_required": "To Time is required",
"something_went_wrong":"Unable to Process"
}

